ansible_mitogen/__init__.py
ansible_mitogen/affinity.py
ansible_mitogen/connection.py
ansible_mitogen/loaders.py
ansible_mitogen/logging.py
ansible_mitogen/mixins.py
ansible_mitogen/module_finder.py
ansible_mitogen/parsing.py
ansible_mitogen/planner.py
ansible_mitogen/process.py
ansible_mitogen/runner.py
ansible_mitogen/services.py
ansible_mitogen/strategy.py
ansible_mitogen/target.py
ansible_mitogen/transport_config.py
ansible_mitogen/compat/__init__.py
ansible_mitogen/plugins/__init__.py
ansible_mitogen/plugins/action/__init__.py
ansible_mitogen/plugins/action/mitogen_fetch.py
ansible_mitogen/plugins/action/mitogen_get_stack.py
ansible_mitogen/plugins/connection/__init__.py
ansible_mitogen/plugins/connection/mitogen_buildah.py
ansible_mitogen/plugins/connection/mitogen_doas.py
ansible_mitogen/plugins/connection/mitogen_docker.py
ansible_mitogen/plugins/connection/mitogen_jail.py
ansible_mitogen/plugins/connection/mitogen_kubectl.py
ansible_mitogen/plugins/connection/mitogen_local.py
ansible_mitogen/plugins/connection/mitogen_lxc.py
ansible_mitogen/plugins/connection/mitogen_lxd.py
ansible_mitogen/plugins/connection/mitogen_machinectl.py
ansible_mitogen/plugins/connection/mitogen_podman.py
ansible_mitogen/plugins/connection/mitogen_setns.py
ansible_mitogen/plugins/connection/mitogen_ssh.py
ansible_mitogen/plugins/connection/mitogen_su.py
ansible_mitogen/plugins/connection/mitogen_sudo.py
ansible_mitogen/plugins/strategy/__init__.py
ansible_mitogen/plugins/strategy/mitogen.py
ansible_mitogen/plugins/strategy/mitogen_free.py
ansible_mitogen/plugins/strategy/mitogen_host_pinned.py
ansible_mitogen/plugins/strategy/mitogen_linear.py
ansible_mitogen/utils/__init__.py
ansible_mitogen/utils/unsafe.py
mitogen/__init__.py
mitogen/buildah.py
mitogen/core.py
mitogen/debug.py
mitogen/doas.py
mitogen/docker.py
mitogen/fakessh.py
mitogen/fork.py
mitogen/jail.py
mitogen/kubectl.py
mitogen/lxc.py
mitogen/lxd.py
mitogen/master.py
mitogen/minify.py
mitogen/os_fork.py
mitogen-0.3.37.dist-info/licenses/LICENSE
mitogen-0.3.37.dist-info/METADATA
mitogen-0.3.37.dist-info/WHEEL
mitogen-0.3.37.dist-info/top_level.txt
mitogen-0.3.37.dist-info/RECORD
